{
  "updates": [
    {
      "steps": 256,
      "meanLoss": 544.4831485748291,
      "meanEpisodeReward": 494.442815322873,
      "meanBaseReward": 1.931417247354972,
      "meanQualityPenalty": 0.0,
      "meanQualityTerms": {
        "jointAcceleration": 0.0,
        "bodyAngularAcceleration": 0.0,
        "actionSlew": 0.0,
        "actuatorSaturation": 0.0,
        "footSlip": 0.0,
        "footImpact": 0.0
      },
      "meanMissionReward": 0.0,
      "meanMissionTerms": {
        "commandProgress": 0.0,
        "velocityTracking": 0.0,
        "stopStability": 0.0
      },
      "meanResidualGateScale": 0.0,
      "meanResidualL2": 0.029589128284631585,
      "activePolicyFraction": 0.0
    },
    {
      "steps": 512,
      "meanLoss": 106.19067001342773,
      "meanEpisodeReward": 681.654619539087,
      "meanBaseReward": 0.7312961102195868,
      "meanQualityPenalty": 0.0,
      "meanQualityTerms": {
        "jointAcceleration": 0.0,
        "bodyAngularAcceleration": 0.0,
        "actionSlew": 0.0,
        "actuatorSaturation": 0.0,
        "footSlip": 0.0,
        "footImpact": 0.0
      },
      "meanMissionReward": 0.0,
      "meanMissionTerms": {
        "commandProgress": 0.0,
        "velocityTracking": 0.0,
        "stopStability": 0.0
      },
      "meanResidualGateScale": 0.0,
      "meanResidualL2": 0.02889425610162482,
      "activePolicyFraction": 0.0
    },
    {
      "steps": 768,
      "meanLoss": 154.076003074646,
      "meanEpisodeReward": 870.5210348604004,
      "meanBaseReward": 0.7377594348488755,
      "meanQualityPenalty": 0.0,
      "meanQualityTerms": {
        "jointAcceleration": 0.0,
        "bodyAngularAcceleration": 0.0,
        "actionSlew": 0.0,
        "actuatorSaturation": 0.0,
        "footSlip": 0.0,
        "footImpact": 0.0
      },
      "meanMissionReward": 0.0,
      "meanMissionTerms": {
        "commandProgress": 0.0,
        "velocityTracking": 0.0,
        "stopStability": 0.0
      },
      "meanResidualGateScale": 0.0,
      "meanResidualL2": 0.02963601608708365,
      "activePolicyFraction": 0.0
    },
    {
      "steps": 1024,
      "meanLoss": 83.83824825286865,
      "meanEpisodeReward": 943.4610332493091,
      "meanBaseReward": 0.7494565098109363,
      "meanQualityPenalty": 0.0,
      "meanQualityTerms": {
        "jointAcceleration": 0.0,
        "bodyAngularAcceleration": 0.0,
        "actionSlew": 0.0,
        "actuatorSaturation": 0.0,
        "footSlip": 0.0,
        "footImpact": 0.0
      },
      "meanMissionReward": 0.0,
      "meanMissionTerms": {
        "commandProgress": 0.0,
        "velocityTracking": 0.0,
        "stopStability": 0.0
      },
      "meanResidualGateScale": 0.0,
      "meanResidualL2": 0.02997001889480775,
      "activePolicyFraction": 0.0
    },
    {
      "steps": 1280,
      "meanLoss": 249.01560974121094,
      "meanEpisodeReward": 943.4610332493091,
      "meanBaseReward": 1.2953285334361737,
      "meanQualityPenalty": 0.0,
      "meanQualityTerms": {
        "jointAcceleration": 0.0,
        "bodyAngularAcceleration": 0.0,
        "actionSlew": 0.0,
        "actuatorSaturation": 0.0,
        "footSlip": 0.0,
        "footImpact": 0.0
      },
      "meanMissionReward": 0.0,
      "meanMissionTerms": {
        "commandProgress": 0.0,
        "velocityTracking": 0.0,
        "stopStability": 0.0
      },
      "meanResidualGateScale": 0.0,
      "meanResidualL2": 0.0297014694168894,
      "activePolicyFraction": 0.0
    },
    {
      "steps": 1536,
      "meanLoss": 98.21447467803955,
      "meanEpisodeReward": 719.8751700787618,
      "meanBaseReward": 0.8583335921579286,
      "meanQualityPenalty": 0.0,
      "meanQualityTerms": {
        "jointAcceleration": 0.0,
        "bodyAngularAcceleration": 0.0,
        "actionSlew": 0.0,
        "actuatorSaturation": 0.0,
        "footSlip": 0.0,
        "footImpact": 0.0
      },
      "meanMissionReward": 0.0,
      "meanMissionTerms": {
        "commandProgress": 0.0,
        "velocityTracking": 0.0,
        "stopStability": 0.0
      },
      "meanResidualGateScale": 0.0,
      "meanResidualL2": 0.02938999668196289,
      "activePolicyFraction": 0.0
    },
    {
      "steps": 1792,
      "meanLoss": 47.38823652267456,
      "meanEpisodeReward": 719.8751700787618,
      "meanBaseReward": 0.6497469681959056,
      "meanQualityPenalty": 0.0,
      "meanQualityTerms": {
        "jointAcceleration": 0.0,
        "bodyAngularAcceleration": 0.0,
        "actionSlew": 0.0,
        "actuatorSaturation": 0.0,
        "footSlip": 0.0,
        "footImpact": 0.0
      },
      "meanMissionReward": 0.0,
      "meanMissionTerms": {
        "commandProgress": 0.0,
        "velocityTracking": 0.0,
        "stopStability": 0.0
      },
      "meanResidualGateScale": 0.0,
      "meanResidualL2": 0.030326770921416345,
      "activePolicyFraction": 0.0
    },
    {
      "steps": 2048,
      "meanLoss": 296.6164493560791,
      "meanEpisodeReward": 595.6807646567081,
      "meanBaseReward": 1.0575945721849782,
      "meanQualityPenalty": 0.0,
      "meanQualityTerms": {
        "jointAcceleration": 0.0,
        "bodyAngularAcceleration": 0.0,
        "actionSlew": 0.0,
        "actuatorSaturation": 0.0,
        "footSlip": 0.0,
        "footImpact": 0.0
      },
      "meanMissionReward": 0.0,
      "meanMissionTerms": {
        "commandProgress": 0.0,
        "velocityTracking": 0.0,
        "stopStability": 0.0
      },
      "meanResidualGateScale": 0.0,
      "meanResidualL2": 0.02893301819166355,
      "activePolicyFraction": 0.0
    },
    {
      "steps": 2304,
      "meanLoss": 90.23562049865723,
      "meanEpisodeReward": 595.6807646567081,
      "meanBaseReward": -0.29086559498173836,
      "meanQualityPenalty": 0.0,
      "meanQualityTerms": {
        "jointAcceleration": 0.0,
        "bodyAngularAcceleration": 0.0,
        "actionSlew": 0.0,
        "actuatorSaturation": 0.0,
        "footSlip": 0.0,
        "footImpact": 0.0
      },
      "meanMissionReward": 0.0,
      "meanMissionTerms": {
        "commandProgress": 0.0,
        "velocityTracking": 0.0,
        "stopStability": 0.0
      },
      "meanResidualGateScale": 0.0,
      "meanResidualL2": 0.02926011283571464,
      "activePolicyFraction": 0.0
    },
    {
      "steps": 2560,
      "meanLoss": 59.328001737594604,
      "meanEpisodeReward": 595.6807646567081,
      "meanBaseReward": 0.6998155588467749,
      "meanQualityPenalty": 0.0,
      "meanQualityTerms": {
        "jointAcceleration": 0.0,
        "bodyAngularAcceleration": 0.0,
        "actionSlew": 0.0,
        "actuatorSaturation": 0.0,
        "footSlip": 0.0,
        "footImpact": 0.0
      },
      "meanMissionReward": 0.0,
      "meanMissionTerms": {
        "commandProgress": 0.0,
        "velocityTracking": 0.0,
        "stopStability": 0.0
      },
      "meanResidualGateScale": 0.0,
      "meanResidualL2": 0.029423491868348972,
      "activePolicyFraction": 0.0
    },
    {
      "steps": 2816,
      "meanLoss": 71.3406229019165,
      "meanEpisodeReward": 572.3146735498606,
      "meanBaseReward": 0.8352675401686049,
      "meanQualityPenalty": 0.0,
      "meanQualityTerms": {
        "jointAcceleration": 0.0,
        "bodyAngularAcceleration": 0.0,
        "actionSlew": 0.0,
        "actuatorSaturation": 0.0,
        "footSlip": 0.0,
        "footImpact": 0.0
      },
      "meanMissionReward": 0.0,
      "meanMissionTerms": {
        "commandProgress": 0.0,
        "velocityTracking": 0.0,
        "stopStability": 0.0
      },
      "meanResidualGateScale": 0.0,
      "meanResidualL2": 0.029674221339047374,
      "activePolicyFraction": 0.0
    },
    {
      "steps": 3072,
      "meanLoss": 106.86239290237427,
      "meanEpisodeReward": 572.3146735498606,
      "meanBaseReward": 0.9709626334241594,
      "meanQualityPenalty": 0.0,
      "meanQualityTerms": {
        "jointAcceleration": 0.0,
        "bodyAngularAcceleration": 0.0,
        "actionSlew": 0.0,
        "actuatorSaturation": 0.0,
        "footSlip": 0.0,
        "footImpact": 0.0
      },
      "meanMissionReward": 0.0,
      "meanMissionTerms": {
        "commandProgress": 0.0,
        "velocityTracking": 0.0,
        "stopStability": 0.0
      },
      "meanResidualGateScale": 0.0,
      "meanResidualL2": 0.029448333678636633,
      "activePolicyFraction": 0.0
    },
    {
      "steps": 3328,
      "meanLoss": 44.268056869506836,
      "meanEpisodeReward": 535.4530593118833,
      "meanBaseReward": 0.6042017660063124,
      "meanQualityPenalty": 0.0,
      "meanQualityTerms": {
        "jointAcceleration": 0.0,
        "bodyAngularAcceleration": 0.0,
        "actionSlew": 0.0,
        "actuatorSaturation": 0.0,
        "footSlip": 0.0,
        "footImpact": 0.0
      },
      "meanMissionReward": 0.0,
      "meanMissionTerms": {
        "commandProgress": 0.0,
        "velocityTracking": 0.0,
        "stopStability": 0.0
      },
      "meanResidualGateScale": 0.0,
      "meanResidualL2": 0.02948785055152038,
      "activePolicyFraction": 0.0
    },
    {
      "steps": 3584,
      "meanLoss": 62.122005224227905,
      "meanEpisodeReward": 535.4530593118833,
      "meanBaseReward": -0.5877003343856795,
      "meanQualityPenalty": 0.0,
      "meanQualityTerms": {
        "jointAcceleration": 0.0,
        "bodyAngularAcceleration": 0.0,
        "actionSlew": 0.0,
        "actuatorSaturation": 0.0,
        "footSlip": 0.0,
        "footImpact": 0.0
      },
      "meanMissionReward": 0.0,
      "meanMissionTerms": {
        "commandProgress": 0.0,
        "velocityTracking": 0.0,
        "stopStability": 0.0
      },
      "meanResidualGateScale": 0.0,
      "meanResidualL2": 0.029384688299847157,
      "activePolicyFraction": 0.0
    },
    {
      "steps": 3840,
      "meanLoss": 376.1585063934326,
      "meanEpisodeReward": 436.62262558894435,
      "meanBaseReward": 1.4888797163335865,
      "meanQualityPenalty": 0.0,
      "meanQualityTerms": {
        "jointAcceleration": 0.0,
        "bodyAngularAcceleration": 0.0,
        "actionSlew": 0.0,
        "actuatorSaturation": 0.0,
        "footSlip": 0.0,
        "footImpact": 0.0
      },
      "meanMissionReward": 0.0,
      "meanMissionTerms": {
        "commandProgress": 0.0,
        "velocityTracking": 0.0,
        "stopStability": 0.0
      },
      "meanResidualGateScale": 0.0,
      "meanResidualL2": 0.029012798927836415,
      "activePolicyFraction": 0.0
    },
    {
      "steps": 4096,
      "meanLoss": 818.7188682261947,
      "meanEpisodeReward": 436.62262558894435,
      "meanBaseReward": 2.5189310463886683,
      "meanQualityPenalty": 0.0,
      "meanQualityTerms": {
        "jointAcceleration": 0.0,
        "bodyAngularAcceleration": 0.0,
        "actionSlew": 0.0,
        "actuatorSaturation": 0.0,
        "footSlip": 0.0,
        "footImpact": 0.0
      },
      "meanMissionReward": 0.05142029529966676,
      "meanMissionTerms": {
        "commandProgress": -0.0008457418390515423,
        "velocityTracking": 0.0522660371387183,
        "stopStability": 0.0
      },
      "meanResidualGateScale": 0.09276041666669113,
      "meanResidualL2": 0.029913121046214484,
      "activePolicyFraction": 0.1640625
    },
    {
      "steps": 4352,
      "meanLoss": 1105.1836989030542,
      "meanEpisodeReward": 436.62262558894435,
      "meanBaseReward": 2.077604690102482,
      "meanQualityPenalty": 0.0,
      "meanQualityTerms": {
        "jointAcceleration": 0.0,
        "bodyAngularAcceleration": 0.0,
        "actionSlew": 0.0,
        "actuatorSaturation": 0.0,
        "footSlip": 0.0,
        "footImpact": 0.0
      },
      "meanMissionReward": 0.5913973250989271,
      "meanMissionTerms": {
        "commandProgress": 0.36188400042600277,
        "velocityTracking": 0.22951332467292423,
        "stopStability": 0.0
      },
      "meanResidualGateScale": 1.0,
      "meanResidualL2": 0.19110569259609572,
      "activePolicyFraction": 1.0
    },
    {
      "steps": 4608,
      "meanLoss": 763.5352029903622,
      "meanEpisodeReward": 692.2388640890593,
      "meanBaseReward": 1.8430186082207558,
      "meanQualityPenalty": 0.0,
      "meanQualityTerms": {
        "jointAcceleration": 0.0,
        "bodyAngularAcceleration": 0.0,
        "actionSlew": 0.0,
        "actuatorSaturation": 0.0,
        "footSlip": 0.0,
        "footImpact": 0.0
      },
      "meanMissionReward": 0.5453334428616537,
      "meanMissionTerms": {
        "commandProgress": 0.16525345025806962,
        "velocityTracking": 0.05048568342859873,
        "stopStability": 0.32959430917498544
      },
      "meanResidualGateScale": 0.578125,
      "meanResidualL2": 0.29496267224808304,
      "activePolicyFraction": 0.578125
    },
    {
      "steps": 4864,
      "meanLoss": 29.77331566810608,
      "meanEpisodeReward": 692.2388640890593,
      "meanBaseReward": 0.4283859015110063,
      "meanQualityPenalty": 0.0,
      "meanQualityTerms": {
        "jointAcceleration": 0.0,
        "bodyAngularAcceleration": 0.0,
        "actionSlew": 0.0,
        "actuatorSaturation": 0.0,
        "footSlip": 0.0,
        "footImpact": 0.0
      },
      "meanMissionReward": 0.0,
      "meanMissionTerms": {
        "commandProgress": 0.0,
        "velocityTracking": 0.0,
        "stopStability": 0.0
      },
      "meanResidualGateScale": 0.0,
      "meanResidualL2": 0.2988464399940226,
      "activePolicyFraction": 0.0
    },
    {
      "steps": 5120,
      "meanLoss": 113.82019376754761,
      "meanEpisodeReward": 640.0578411492852,
      "meanBaseReward": 0.9036702628555611,
      "meanQualityPenalty": 0.0,
      "meanQualityTerms": {
        "jointAcceleration": 0.0,
        "bodyAngularAcceleration": 0.0,
        "actionSlew": 0.0,
        "actuatorSaturation": 0.0,
        "footSlip": 0.0,
        "footImpact": 0.0
      },
      "meanMissionReward": 0.0,
      "meanMissionTerms": {
        "commandProgress": 0.0,
        "velocityTracking": 0.0,
        "stopStability": 0.0
      },
      "meanResidualGateScale": 0.0,
      "meanResidualL2": 0.301364241547731,
      "activePolicyFraction": 0.0
    },
    {
      "steps": 5376,
      "meanLoss": 40.8662474155426,
      "meanEpisodeReward": 640.0578411492852,
      "meanBaseReward": 0.6455685757409528,
      "meanQualityPenalty": 0.0,
      "meanQualityTerms": {
        "jointAcceleration": 0.0,
        "bodyAngularAcceleration": 0.0,
        "actionSlew": 0.0,
        "actuatorSaturation": 0.0,
        "footSlip": 0.0,
        "footImpact": 0.0
      },
      "meanMissionReward": 0.0,
      "meanMissionTerms": {
        "commandProgress": 0.0,
        "velocityTracking": 0.0,
        "stopStability": 0.0
      },
      "meanResidualGateScale": 0.0,
      "meanResidualL2": 0.30800226006542175,
      "activePolicyFraction": 0.0
    },
    {
      "steps": 5632,
      "meanLoss": 85.71895742416382,
      "meanEpisodeReward": 608.58691230565,
      "meanBaseReward": 0.8046566342224146,
      "meanQualityPenalty": 0.0,
      "meanQualityTerms": {
        "jointAcceleration": 0.0,
        "bodyAngularAcceleration": 0.0,
        "actionSlew": 0.0,
        "actuatorSaturation": 0.0,
        "footSlip": 0.0,
        "footImpact": 0.0
      },
      "meanMissionReward": 0.0,
      "meanMissionTerms": {
        "commandProgress": 0.0,
        "velocityTracking": 0.0,
        "stopStability": 0.0
      },
      "meanResidualGateScale": 0.0,
      "meanResidualL2": 0.3085810173867798,
      "activePolicyFraction": 0.0
    },
    {
      "steps": 5888,
      "meanLoss": 140.96884775161743,
      "meanEpisodeReward": 585.0862551139105,
      "meanBaseReward": 1.1585234880554234,
      "meanQualityPenalty": 0.0,
      "meanQualityTerms": {
        "jointAcceleration": 0.0,
        "bodyAngularAcceleration": 0.0,
        "actionSlew": 0.0,
        "actuatorSaturation": 0.0,
        "footSlip": 0.0,
        "footImpact": 0.0
      },
      "meanMissionReward": 0.0,
      "meanMissionTerms": {
        "commandProgress": 0.0,
        "velocityTracking": 0.0,
        "stopStability": 0.0
      },
      "meanResidualGateScale": 0.0,
      "meanResidualL2": 0.31015791788801217,
      "activePolicyFraction": 0.0
    },
    {
      "steps": 6144,
      "meanLoss": 397.3759536743164,
      "meanEpisodeReward": 585.0862551139105,
      "meanBaseReward": 1.7733833886110764,
      "meanQualityPenalty": 0.0,
      "meanQualityTerms": {
        "jointAcceleration": 0.0,
        "bodyAngularAcceleration": 0.0,
        "actionSlew": 0.0,
        "actuatorSaturation": 0.0,
        "footSlip": 0.0,
        "footImpact": 0.0
      },
      "meanMissionReward": 0.0,
      "meanMissionTerms": {
        "commandProgress": 0.0,
        "velocityTracking": 0.0,
        "stopStability": 0.0
      },
      "meanResidualGateScale": 0.0,
      "meanResidualL2": 0.3102117827930736,
      "activePolicyFraction": 0.0
    },
    {
      "steps": 6400,
      "meanLoss": 77.30644512176514,
      "meanEpisodeReward": 585.0862551139105,
      "meanBaseReward": 0.8290628100951094,
      "meanQualityPenalty": 0.0,
      "meanQualityTerms": {
        "jointAcceleration": 0.0,
        "bodyAngularAcceleration": 0.0,
        "actionSlew": 0.0,
        "actuatorSaturation": 0.0,
        "footSlip": 0.0,
        "footImpact": 0.0
      },
      "meanMissionReward": 0.0,
      "meanMissionTerms": {
        "commandProgress": 0.0,
        "velocityTracking": 0.0,
        "stopStability": 0.0
      },
      "meanResidualGateScale": 0.0,
      "meanResidualL2": 0.3107838450855349,
      "activePolicyFraction": 0.0
    },
    {
      "steps": 6656,
      "meanLoss": 114.58175611495972,
      "meanEpisodeReward": 585.0862551139105,
      "meanBaseReward": 1.04644282411599,
      "meanQualityPenalty": 0.0,
      "meanQualityTerms": {
        "jointAcceleration": 0.0,
        "bodyAngularAcceleration": 0.0,
        "actionSlew": 0.0,
        "actuatorSaturation": 0.0,
        "footSlip": 0.0,
        "footImpact": 0.0
      },
      "meanMissionReward": 0.0,
      "meanMissionTerms": {
        "commandProgress": 0.0,
        "velocityTracking": 0.0,
        "stopStability": 0.0
      },
      "meanResidualGateScale": 0.0,
      "meanResidualL2": 0.31206883291713383,
      "activePolicyFraction": 0.0
    },
    {
      "steps": 6912,
      "meanLoss": 653.6619071960449,
      "meanEpisodeReward": 609.6219418790217,
      "meanBaseReward": 2.198908951275672,
      "meanQualityPenalty": 0.0,
      "meanQualityTerms": {
        "jointAcceleration": 0.0,
        "bodyAngularAcceleration": 0.0,
        "actionSlew": 0.0,
        "actuatorSaturation": 0.0,
        "footSlip": 0.0,
        "footImpact": 0.0
      },
      "meanMissionReward": 0.0,
      "meanMissionTerms": {
        "commandProgress": 0.0,
        "velocityTracking": 0.0,
        "stopStability": 0.0
      },
      "meanResidualGateScale": 0.0,
      "meanResidualL2": 0.3111787878714297,
      "activePolicyFraction": 0.0
    },
    {
      "steps": 7168,
      "meanLoss": 380.3932418823242,
      "meanEpisodeReward": 609.6219418790217,
      "meanBaseReward": 1.749132352286734,
      "meanQualityPenalty": 0.0,
      "meanQualityTerms": {
        "jointAcceleration": 0.0,
        "bodyAngularAcceleration": 0.0,
        "actionSlew": 0.0,
        "actuatorSaturation": 0.0,
        "footSlip": 0.0,
        "footImpact": 0.0
      },
      "meanMissionReward": 0.0,
      "meanMissionTerms": {
        "commandProgress": 0.0,
        "velocityTracking": 0.0,
        "stopStability": 0.0
      },
      "meanResidualGateScale": 0.0,
      "meanResidualL2": 0.3114502481385121,
      "activePolicyFraction": 0.0
    },
    {
      "steps": 7424,
      "meanLoss": 513.2618713378906,
      "meanEpisodeReward": 609.6219418790217,
      "meanBaseReward": 2.0958906575997,
      "meanQualityPenalty": 0.0,
      "meanQualityTerms": {
        "jointAcceleration": 0.0,
        "bodyAngularAcceleration": 0.0,
        "actionSlew": 0.0,
        "actuatorSaturation": 0.0,
        "footSlip": 0.0,
        "footImpact": 0.0
      },
      "meanMissionReward": 0.0,
      "meanMissionTerms": {
        "commandProgress": 0.0,
        "velocityTracking": 0.0,
        "stopStability": 0.0
      },
      "meanResidualGateScale": 0.0,
      "meanResidualL2": 0.31144944555503595,
      "activePolicyFraction": 0.0
    },
    {
      "steps": 7680,
      "meanLoss": 449.1650085449219,
      "meanEpisodeReward": 746.0705562644032,
      "meanBaseReward": 2.1372893853056487,
      "meanQualityPenalty": 0.0,
      "meanQualityTerms": {
        "jointAcceleration": 0.0,
        "bodyAngularAcceleration": 0.0,
        "actionSlew": 0.0,
        "actuatorSaturation": 0.0,
        "footSlip": 0.0,
        "footImpact": 0.0
      },
      "meanMissionReward": 0.0,
      "meanMissionTerms": {
        "commandProgress": 0.0,
        "velocityTracking": 0.0,
        "stopStability": 0.0
      },
      "meanResidualGateScale": 0.0,
      "meanResidualL2": 0.3124907725786615,
      "activePolicyFraction": 0.0
    },
    {
      "steps": 7936,
      "meanLoss": 301.6968288421631,
      "meanEpisodeReward": 746.0705562644032,
      "meanBaseReward": 1.2340057399272841,
      "meanQualityPenalty": 0.0,
      "meanQualityTerms": {
        "jointAcceleration": 0.0,
        "bodyAngularAcceleration": 0.0,
        "actionSlew": 0.0,
        "actuatorSaturation": 0.0,
        "footSlip": 0.0,
        "footImpact": 0.0
      },
      "meanMissionReward": 0.0,
      "meanMissionTerms": {
        "commandProgress": 0.0,
        "velocityTracking": 0.0,
        "stopStability": 0.0
      },
      "meanResidualGateScale": 0.0,
      "meanResidualL2": 0.31300341170078017,
      "activePolicyFraction": 0.0
    },
    {
      "steps": 8192,
      "meanLoss": 82.31508827209473,
      "meanEpisodeReward": 746.0705562644032,
      "meanBaseReward": 0.3042641228573277,
      "meanQualityPenalty": 0.0,
      "meanQualityTerms": {
        "jointAcceleration": 0.0,
        "bodyAngularAcceleration": 0.0,
        "actionSlew": 0.0,
        "actuatorSaturation": 0.0,
        "footSlip": 0.0,
        "footImpact": 0.0
      },
      "meanMissionReward": 0.0,
      "meanMissionTerms": {
        "commandProgress": 0.0,
        "velocityTracking": 0.0,
        "stopStability": 0.0
      },
      "meanResidualGateScale": 0.0,
      "meanResidualL2": 0.31314140995095247,
      "activePolicyFraction": 0.0
    }
  ],
  "totalSteps": 8192,
  "episodes": 12,
  "finalMeanEpisodeReward": 746.0705562644032,
  "qualityRewardReferences": {
    "jointAcceleration": 1000.0,
    "bodyAngularAcceleration": 100.0,
    "actionSlew": 800.0,
    "actuatorSaturation": 1.0,
    "footSlip": 1.0,
    "footImpact": 20000.0
  },
  "domainProfile": {
    "id": "quadruped-resilient-mission-v1",
    "hash": "6a897a4e16f28a2c21046e86610a9ac564201710204cd776af682c5603ba9af8",
    "evidenceHash": null,
    "provenance": {
      "kind": "synthetic",
      "evidence": null,
      "notes": "Training-only engineering envelope. Impact time, magnitude, and planar direction vary continuously around two authored opposing base directions; plant ranges remain synthetic until replaced by HIL or real identification."
    }
  },
  "domainSamples": [
    {
      "episode": 1,
      "curriculum": "integrated-mission",
      "role": "mission",
      "task": "integrated-resilience-mission",
      "scenario": "mission-impact-left",
      "environmentSeed": 260729,
      "domainSeed": 10260729,
      "steps": 900,
      "completed": true,
      "parameters": {
        "bodyMassScale": 1.0059191457443415,
        "jointDampingScale": 0.8917559046993937,
        "actuatorStrengthScale": 0.9261294441131229,
        "frictionScale": 0.9492529144701178,
        "observationNoiseStd": 0.0003065713938755854,
        "actuatorDelayJitterSteps": 1,
        "pushTimeOffsetSeconds": -0.23453718383227917,
        "pushForceScale": 0.9075404277735325,
        "pushDirectionJitterRad": 0.0028515141583698167
      }
    },
    {
      "episode": 2,
      "curriculum": "recovery-handoff-skill",
      "role": "skill",
      "task": "recover-forward",
      "scenario": "fallen-front",
      "environmentSeed": 260730,
      "domainSeed": 10260730,
      "steps": 450,
      "completed": true,
      "parameters": {
        "bodyMassScale": 0.9226137704331056,
        "jointDampingScale": 1.223973503462331,
        "actuatorStrengthScale": 1.0835199756407083,
        "frictionScale": 0.986194403813104,
        "observationNoiseStd": 0.0018296910368510372,
        "actuatorDelayJitterSteps": 1,
        "pushTimeOffsetSeconds": 0.26104963259739183,
        "pushForceScale": 0.9744588985423952,
        "pushDirectionJitterRad": 0.24797274340877123
      }
    },
    {
      "episode": 3,
      "curriculum": "recovery-handoff-skill",
      "role": "skill",
      "task": "recover-forward",
      "scenario": "fallen-back",
      "environmentSeed": 260731,
      "domainSeed": 10260731,
      "steps": 450,
      "completed": true,
      "parameters": {
        "bodyMassScale": 0.9313772246099709,
        "jointDampingScale": 1.1489737070519013,
        "actuatorStrengthScale": 1.0111528270364247,
        "frictionScale": 1.0869496372979448,
        "observationNoiseStd": 0.000570938443386776,
        "actuatorDelayJitterSteps": 1,
        "pushTimeOffsetSeconds": -0.2630154587911819,
        "pushForceScale": 0.9426260243797417,
        "pushDirectionJitterRad": -0.14310649692762867
      }
    },
    {
      "episode": 4,
      "curriculum": "integrated-mission",
      "role": "mission",
      "task": "integrated-resilience-mission",
      "scenario": "mission-impact-right",
      "environmentSeed": 260732,
      "domainSeed": 10260732,
      "steps": 900,
      "completed": true,
      "parameters": {
        "bodyMassScale": 0.9266448211946322,
        "jointDampingScale": 1.0693860747958919,
        "actuatorStrengthScale": 0.9847212629658062,
        "frictionScale": 1.1172846772345533,
        "observationNoiseStd": 0.0008382345415663624,
        "actuatorDelayJitterSteps": 1,
        "pushTimeOffsetSeconds": 0.09637085284018491,
        "pushForceScale": 0.8108013429401343,
        "pushDirectionJitterRad": 0.1793070402167367
      }
    },
    {
      "episode": 5,
      "curriculum": "recovery-handoff-skill",
      "role": "skill",
      "task": "recover-forward",
      "scenario": "fallen-left",
      "environmentSeed": 260733,
      "domainSeed": 10260733,
      "steps": 450,
      "completed": true,
      "parameters": {
        "bodyMassScale": 0.9826460596030056,
        "jointDampingScale": 0.8128712652009187,
        "actuatorStrengthScale": 0.9522097549506497,
        "frictionScale": 1.047879791426307,
        "observationNoiseStd": 0.00101447124955528,
        "actuatorDelayJitterSteps": 1,
        "pushTimeOffsetSeconds": -0.24150039894353864,
        "pushForceScale": 1.1143025579389856,
        "pushDirectionJitterRad": -0.16216380570328992
      }
    },
    {
      "episode": 6,
      "curriculum": "recovery-handoff-skill",
      "role": "skill",
      "task": "recover-forward",
      "scenario": "fallen-right",
      "environmentSeed": 260734,
      "domainSeed": 10260734,
      "steps": 450,
      "completed": true,
      "parameters": {
        "bodyMassScale": 0.9223869349717893,
        "jointDampingScale": 0.7520908626431944,
        "actuatorStrengthScale": 0.9050883468433366,
        "frictionScale": 0.893303803942466,
        "observationNoiseStd": 0.0017915871458596467,
        "actuatorDelayJitterSteps": 1,
        "pushTimeOffsetSeconds": -0.0009574812082135508,
        "pushForceScale": 1.069211676745664,
        "pushDirectionJitterRad": 0.16291501959303392
      }
    },
    {
      "episode": 7,
      "curriculum": "integrated-mission",
      "role": "mission",
      "task": "integrated-resilience-mission",
      "scenario": "mission-impact-left",
      "environmentSeed": 260735,
      "domainSeed": 10260735,
      "steps": 900,
      "completed": true,
      "parameters": {
        "bodyMassScale": 0.9896210012378674,
        "jointDampingScale": 0.8156248984490495,
        "actuatorStrengthScale": 0.9810853184144844,
        "frictionScale": 1.0133803577107687,
        "observationNoiseStd": 0.0006560373977873763,
        "actuatorDelayJitterSteps": 0,
        "pushTimeOffsetSeconds": -0.21975165864039728,
        "pushForceScale": 1.1056041749836962,
        "pushDirectionJitterRad": 0.11623627707673678
      }
    },
    {
      "episode": 8,
      "curriculum": "recovery-handoff-skill",
      "role": "skill",
      "task": "recover-forward",
      "scenario": "fallen-front",
      "environmentSeed": 260736,
      "domainSeed": 10260736,
      "steps": 450,
      "completed": true,
      "parameters": {
        "bodyMassScale": 1.0265556909881328,
        "jointDampingScale": 1.1691604036904295,
        "actuatorStrengthScale": 0.9764768921696345,
        "frictionScale": 1.0274444413742345,
        "observationNoiseStd": 0.001366482258695113,
        "actuatorDelayJitterSteps": 1,
        "pushTimeOffsetSeconds": 0.1863021127203777,
        "pushForceScale": 0.9685780544470428,
        "pushDirectionJitterRad": 0.16816132449330679
      }
    },
    {
      "episode": 9,
      "curriculum": "recovery-handoff-skill",
      "role": "skill",
      "task": "recover-forward",
      "scenario": "fallen-back",
      "environmentSeed": 260737,
      "domainSeed": 10260737,
      "steps": 450,
      "completed": true,
      "parameters": {
        "bodyMassScale": 1.0459927970700351,
        "jointDampingScale": 1.085019115137798,
        "actuatorStrengthScale": 1.0387052890056456,
        "frictionScale": 1.0149519462004872,
        "observationNoiseStd": 0.0012041690119739723,
        "actuatorDelayJitterSteps": 1,
        "pushTimeOffsetSeconds": -0.06258101529507232,
        "pushForceScale": 0.7545962267865659,
        "pushDirectionJitterRad": 0.16955753232456727
      }
    },
    {
      "episode": 10,
      "curriculum": "recovery-handoff-skill",
      "role": "skill",
      "task": "recover-forward",
      "scenario": "fallen-left",
      "environmentSeed": 260738,
      "domainSeed": 10260738,
      "steps": 450,
      "completed": true,
      "parameters": {
        "bodyMassScale": 0.9677678535364799,
        "jointDampingScale": 0.8229400820606101,
        "actuatorStrengthScale": 0.9569818249203039,
        "frictionScale": 0.9304171139011667,
        "observationNoiseStd": 0.0018375983864711732,
        "actuatorDelayJitterSteps": 0,
        "pushTimeOffsetSeconds": -0.016107096577042433,
        "pushForceScale": 0.7929971225004258,
        "pushDirectionJitterRad": -0.006768669787974235
      }
    },
    {
      "episode": 11,
      "curriculum": "integrated-mission",
      "role": "mission",
      "task": "integrated-resilience-mission",
      "scenario": "mission-impact-right",
      "environmentSeed": 260739,
      "domainSeed": 10260739,
      "steps": 900,
      "completed": true,
      "parameters": {
        "bodyMassScale": 0.9780930482316575,
        "jointDampingScale": 0.8825539637145825,
        "actuatorStrengthScale": 0.9713180136320696,
        "frictionScale": 0.8071877110744978,
        "observationNoiseStd": 0.00019903694250784421,
        "actuatorDelayJitterSteps": 0,
        "pushTimeOffsetSeconds": 0.10795903415695003,
        "pushForceScale": 1.033648463514203,
        "pushDirectionJitterRad": 0.11217376522704187
      }
    },
    {
      "episode": 12,
      "curriculum": "integrated-mission",
      "role": "mission",
      "task": "integrated-resilience-mission",
      "scenario": "mission-impact-left",
      "environmentSeed": 260740,
      "domainSeed": 10260740,
      "steps": 900,
      "completed": true,
      "parameters": {
        "bodyMassScale": 1.0191686180238018,
        "jointDampingScale": 0.8152151674048187,
        "actuatorStrengthScale": 1.0666950884330828,
        "frictionScale": 0.9491701347974199,
        "observationNoiseStd": 0.000826807948193953,
        "actuatorDelayJitterSteps": 0,
        "pushTimeOffsetSeconds": -0.19927598925567716,
        "pushForceScale": 1.0216179670702181,
        "pushDirectionJitterRad": -0.24539350441193108
      }
    },
    {
      "episode": 13,
      "curriculum": "integrated-mission",
      "role": "mission",
      "task": "integrated-resilience-mission",
      "scenario": "mission-impact-right",
      "environmentSeed": 260741,
      "domainSeed": 10260741,
      "steps": 542,
      "completed": false,
      "parameters": {
        "bodyMassScale": 1.0336770375506827,
        "jointDampingScale": 1.051437552807042,
        "actuatorStrengthScale": 0.9239912210795898,
        "frictionScale": 0.8305678035199788,
        "observationNoiseStd": 0.0013168915472256655,
        "actuatorDelayJitterSteps": 0,
        "pushTimeOffsetSeconds": 0.24095157452989768,
        "pushForceScale": 1.2290700408909259,
        "pushDirectionJitterRad": 0.1630144163329464
      }
    }
  ],
  "domainCoverage": {
    "bodyMassScale": {
      "minimum": 0.9223869349717893,
      "mean": 0.9809587694765771,
      "maximum": 1.0459927970700351
    },
    "jointDampingScale": {
      "minimum": 0.7520908626431944,
      "mean": 0.9646925000859972,
      "maximum": 1.223973503462331
    },
    "actuatorStrengthScale": {
      "minimum": 0.9050883468433366,
      "mean": 0.9829288660926814,
      "maximum": 1.0835199756407083
    },
    "frictionScale": {
      "minimum": 0.8071877110744978,
      "mean": 0.9733834412894651,
      "maximum": 1.1172846772345533
    },
    "observationNoiseStd": {
      "minimum": 0.00019903694250784421,
      "mean": 0.0010583474849192144,
      "maximum": 0.0018375983864711732
    },
    "actuatorDelayJitterSteps": {
      "minimum": 0.0,
      "mean": 0.6153846153846154,
      "maximum": 1.0
    },
    "pushTimeOffsetSeconds": {
      "minimum": -0.2630154587911819,
      "mean": -0.026545621207584635,
      "maximum": 0.26104963259739183
    },
    "pushForceScale": {
      "minimum": 0.7545962267865659,
      "mean": 0.9788502291164255,
      "maximum": 1.2290700408909259
    },
    "pushDirectionJitterRad": {
      "minimum": -0.24539350441193108,
      "mean": 0.05882747353851438,
      "maximum": 0.24797274340877123
    }
  },
  "curriculumCoverage": {
    "recovery-handoff-skill": {
      "role": "skill",
      "weight": 0.35,
      "episodesStarted": 7,
      "episodesCompleted": 7,
      "steps": 3150
    },
    "integrated-mission": {
      "role": "mission",
      "weight": 0.65,
      "episodesStarted": 6,
      "episodesCompleted": 5,
      "steps": 5042
    }
  },
  "missionPhaseCoverage": {
    "integrated-mission:approach": {
      "curriculum": "integrated-mission",
      "role": "mission",
      "task": "integrated-resilience-mission",
      "phase": "approach",
      "intent": "operate",
      "steps": 750,
      "activePolicySteps": 0,
      "activePolicyFraction": 0.0,
      "meanActorAuthority": 0.0,
      "meanBaseReward": 2.5341923026111925,
      "meanMissionReward": 0.0,
      "meanLearningReward": 2.5341923026111925,
      "meanQualityPenalty": 0.0,
      "commandedProgressM": 1.1504221091417126
    },
    "integrated-mission:impact": {
      "curriculum": "integrated-mission",
      "role": "mission",
      "task": "integrated-resilience-mission",
      "phase": "impact",
      "intent": "disturbance",
      "steps": 48,
      "activePolicySteps": 0,
      "activePolicyFraction": 0.0,
      "meanActorAuthority": 0.0,
      "meanBaseReward": 1.9729898122905298,
      "meanMissionReward": 0.0,
      "meanLearningReward": 1.9729898122905298,
      "meanQualityPenalty": 0.0,
      "commandedProgressM": 0.08274053415631362
    },
    "integrated-mission:recover": {
      "curriculum": "integrated-mission",
      "role": "mission",
      "task": "integrated-resilience-mission",
      "phase": "recover",
      "intent": "recover",
      "steps": 1602,
      "activePolicySteps": 0,
      "activePolicyFraction": 0.0,
      "meanActorAuthority": 0.0,
      "meanBaseReward": 0.8413036907055772,
      "meanMissionReward": 0.0,
      "meanLearningReward": 0.8413036907055772,
      "meanQualityPenalty": 0.0,
      "commandedProgressM": 2.116762425864432
    },
    "integrated-mission:resume": {
      "curriculum": "integrated-mission",
      "role": "mission",
      "task": "integrated-resilience-mission",
      "phase": "resume",
      "intent": "resume",
      "steps": 600,
      "activePolicySteps": 46,
      "activePolicyFraction": 0.07666666666666666,
      "meanActorAuthority": 0.009248888888890977,
      "meanBaseReward": 1.350771405128397,
      "meanMissionReward": 0.020835271394163715,
      "meanLearningReward": 1.3716066765225612,
      "meanQualityPenalty": 0.0,
      "commandedProgressM": -0.6891425914570655
    },
    "integrated-mission:redirect": {
      "curriculum": "integrated-mission",
      "role": "mission",
      "task": "integrated-resilience-mission",
      "phase": "redirect",
      "intent": "operate",
      "steps": 792,
      "activePolicySteps": 150,
      "activePolicyFraction": 0.1893939393939394,
      "meanActorAuthority": 0.03787878787878778,
      "meanBaseReward": 1.028439676046755,
      "meanMissionReward": 0.020508630371856573,
      "meanLearningReward": 1.0489483064186116,
      "meanQualityPenalty": 0.0,
      "commandedProgressM": -1.0630355250798385
    },
    "integrated-mission:traverse": {
      "curriculum": "integrated-mission",
      "role": "mission",
      "task": "integrated-resilience-mission",
      "phase": "traverse",
      "intent": "operate",
      "steps": 750,
      "activePolicySteps": 150,
      "activePolicyFraction": 0.2,
      "meanActorAuthority": 0.039999999999999904,
      "meanBaseReward": 1.5669426018539323,
      "meanMissionReward": 0.2547287079397578,
      "meanLearningReward": 1.821671309793693,
      "meanQualityPenalty": 0.0,
      "commandedProgressM": 0.8185998286485623
    },
    "integrated-mission:stop": {
      "curriculum": "integrated-mission",
      "role": "mission",
      "task": "integrated-resilience-mission",
      "phase": "stop",
      "intent": "stop",
      "steps": 500,
      "activePolicySteps": 100,
      "activePolicyFraction": 0.2,
      "meanActorAuthority": 0.039999999999999925,
      "meanBaseReward": 1.5207614688582674,
      "meanMissionReward": 0.1687522862975926,
      "meanLearningReward": 1.6895137551558608,
      "meanQualityPenalty": 0.0,
      "commandedProgressM": 0.0
    }
  }
}
