{
  "verdict": "REVERT",
  "decision": {
    "verdict": "REVERT",
    "gateReasons": [
      "light-strong: forward-progress regressed from passing to failing",
      "light-strong: signed-forward-progress regressed from passing to failing",
      "light-strong: backward-displacement regressed from passing to failing",
      "light-strong: planar-velocity-tracking regressed from passing to failing"
    ],
    "previousViolationCount": 12,
    "candidateViolationCount": 16,
    "previousViolationSeverity": 31.9897674006866,
    "candidateViolationSeverity": 39.79884277207508,
    "feasibilityImproved": false,
    "severityImproved": false,
    "scoreImproved": false,
    "selectionReason": "gate-regression"
  },
  "revisionId": null
}
