{
  "durationSeconds": 6.499999999999506,
  "steps": 325,
  "survivalRate": 1.0,
  "fell": false,
  "motionCommand": [
    0.030769230769230813,
    0.0,
    0.0
  ],
  "meanMotionCommand": [
    0.030769230769230813,
    0.0,
    0.0
  ],
  "meanMeasuredMotion": [
    0.05387008342504395,
    0.007212006860904556,
    0.013295011977789895
  ],
  "planarVelocityTrackingError": 0.024200463557281778,
  "yawRateTrackingError": 0.013295011977789895,
  "meanVelocityTrackingError": 0.3149232215085102,
  "meanPlanarVelocityTrackingError": 0.25341083482765675,
  "meanYawRateTrackingError": 0.086080586256882,
  "meanUpright": 0.6017727270106088,
  "meanEnergy": 617.9587992774873,
  "meanSmoothness": 29.168644784442098,
  "peakActuator": 8.0,
  "motionCommandSchedule": [
    {
      "atStep": 0,
      "atSeconds": 0.0,
      "command": [
        0.2,
        0.0,
        0.0
      ]
    },
    {
      "atStep": 125,
      "atSeconds": 2.5,
      "command": [
        -0.15,
        0.0,
        0.0
      ]
    },
    {
      "atStep": 225,
      "atSeconds": 4.5,
      "command": [
        0.0,
        0.0,
        0.0
      ]
    }
  ],
  "transitionCount": 2,
  "transitions": [
    {
      "index": 1,
      "atStep": 125,
      "atSeconds": 2.5,
      "endStep": 225,
      "fromCommand": [
        0.2,
        0.0,
        0.0
      ],
      "toCommand": [
        -0.15,
        0.0,
        0.0
      ],
      "sampleCount": 100,
      "peakPlanarTrackingError": 0.5355442815962583,
      "peakYawRateTrackingError": 8.021905739966721e-10,
      "terminalMeasuredMotion": [
        0.05405621145162372,
        -1.1074210342442759e-10,
        2.3340571732572444e-10
      ],
      "terminalPlanarTrackingError": 0.20405621145162373,
      "terminalYawRateTrackingError": 2.3340571732572444e-10,
      "planarOvershootMps": 0.1618536868861636,
      "yawRateOvershootRadPerSec": 0.0,
      "planarSettlingTimeSeconds": 2.0,
      "yawRateSettlingTimeSeconds": 0.2,
      "planarSettled": false,
      "yawRateSettled": true
    },
    {
      "index": 2,
      "atStep": 225,
      "atSeconds": 4.5,
      "endStep": 325,
      "fromCommand": [
        -0.15,
        0.0,
        0.0
      ],
      "toCommand": [
        0.0,
        0.0,
        0.0
      ],
      "sampleCount": 100,
      "peakPlanarTrackingError": 0.5923392978801748,
      "peakYawRateTrackingError": 2.1636389724009835,
      "terminalMeasuredMotion": [
        0.051223399181011556,
        0.18055010381737185,
        0.11039909644549173
      ],
      "terminalPlanarTrackingError": 0.18767572195710613,
      "terminalYawRateTrackingError": 0.11039909644549173,
      "planarOvershootMps": 0.45240015109607534,
      "yawRateOvershootRadPerSec": 0.0,
      "planarSettlingTimeSeconds": 2.0,
      "yawRateSettlingTimeSeconds": 1.86,
      "planarSettled": false,
      "yawRateSettled": true
    }
  ],
  "maximumTransitionTerminalPlanarTrackingError": 0.20405621145162373,
  "maximumTransitionTerminalYawRateTrackingError": 0.11039909644549173,
  "maximumPlanarSettlingTimeSeconds": 2.0,
  "maximumYawRateSettlingTimeSeconds": 1.86,
  "maximumPlanarOvershootMps": 0.45240015109607534,
  "maximumYawRateOvershootRadPerSec": 0.0,
  "unsettledPlanarTransitionCount": 2,
  "unsettledYawRateTransitionCount": 0,
  "initialBasePosition": [
    0.0,
    0.0,
    0.44
  ],
  "finalBasePosition": [
    0.3575039299306478,
    0.04619387370484859,
    0.26093228947309605
  ],
  "netDisplacement": [
    0.3575039299306478,
    0.04619387370484859,
    -0.17906771052690396
  ],
  "targetPlanarDisplacement": [
    0.2,
    0.0
  ],
  "forwardDisplacement": 0.3575039299306478,
  "targetDistance": 0.2,
  "forwardProgress": 1.0,
  "meanForwardVelocity": 0.05500060460471922,
  "lateralDrift": 0.04619387370484859,
  "distanceTraveled": 1.4038609405144722
}
