{
  "updates": [
    {
      "steps": 512,
      "meanLoss": 1155.4109601498178,
      "meanEpisodeReward": 748.0741825220684
    },
    {
      "steps": 1024,
      "meanLoss": 1140.5496438650503,
      "meanEpisodeReward": 749.2179158639271
    },
    {
      "steps": 1536,
      "meanLoss": 908.8064692212006,
      "meanEpisodeReward": 623.2806636326612
    },
    {
      "steps": 2048,
      "meanLoss": 1059.0226549285803,
      "meanEpisodeReward": 652.4262120891731
    },
    {
      "steps": 2560,
      "meanLoss": 983.9721484339134,
      "meanEpisodeReward": 669.0031956571717
    },
    {
      "steps": 3072,
      "meanLoss": 897.9410275229882,
      "meanEpisodeReward": 588.0930294443582
    },
    {
      "steps": 3584,
      "meanLoss": 1149.8622070323531,
      "meanEpisodeReward": 598.2238776006255
    },
    {
      "steps": 4096,
      "meanLoss": 743.1060702312147,
      "meanEpisodeReward": 588.4706980241774
    }
  ],
  "totalSteps": 4096,
  "episodes": 18,
  "finalMeanEpisodeReward": 588.4706980241774
}
