{
  "updates": [
    {
      "steps": 256,
      "meanLoss": 784.0188000965086,
      "meanEpisodeReward": 393.5301613890467
    },
    {
      "steps": 512,
      "meanLoss": 689.55794687976,
      "meanEpisodeReward": 391.534876303462
    },
    {
      "steps": 768,
      "meanLoss": 732.2803712899995,
      "meanEpisodeReward": 392.41871131150276
    },
    {
      "steps": 1024,
      "meanLoss": 764.0017760030476,
      "meanEpisodeReward": 391.65443334361083
    },
    {
      "steps": 1280,
      "meanLoss": 704.8938105137013,
      "meanEpisodeReward": 392.1302816717177
    },
    {
      "steps": 1536,
      "meanLoss": 704.313166780754,
      "meanEpisodeReward": 391.8336307887086
    },
    {
      "steps": 1792,
      "meanLoss": 757.6324471044131,
      "meanEpisodeReward": 391.8493378229212
    },
    {
      "steps": 2048,
      "meanLoss": 754.3880022622795,
      "meanEpisodeReward": 391.8806647431948
    }
  ],
  "totalSteps": 2048,
  "episodes": 13,
  "finalMeanEpisodeReward": 391.8806647431948
}
