{
  "durationSeconds": 1.9000000000000015,
  "steps": 95,
  "survivalRate": 0.376,
  "fell": true,
  "motionCommand": [
    0.25,
    0.0,
    0.0
  ],
  "meanMotionCommand": [
    0.25,
    0.0,
    0.0
  ],
  "meanMeasuredMotion": [
    0.1932896506941411,
    -0.009491195928686835,
    -5.734259009176638e-05
  ],
  "planarVelocityTrackingError": 0.05749910015425677,
  "yawRateTrackingError": 5.734259009176638e-05,
  "meanVelocityTrackingError": 0.19300398801877147,
  "meanPlanarVelocityTrackingError": 0.16820826958239585,
  "meanYawRateTrackingError": 0.03972512165933602,
  "meanUpright": 0.5535200406169689,
  "meanEnergy": 566.3743175019247,
  "meanSmoothness": 27.76373580547069,
  "peakActuator": 8.0,
  "motionCommandSchedule": [
    {
      "atStep": 0,
      "atSeconds": 0.0,
      "command": [
        0.25,
        0.0,
        0.0
      ]
    }
  ],
  "transitionCount": 0,
  "transitions": [],
  "maximumTransitionTerminalPlanarTrackingError": 0.0,
  "maximumTransitionTerminalYawRateTrackingError": 0.0,
  "maximumPlanarSettlingTimeSeconds": 0.0,
  "maximumPlanarBrakingSettlingTimeSeconds": 0.0,
  "maximumYawRateSettlingTimeSeconds": 0.0,
  "maximumPlanarOvershootMps": 0.0,
  "maximumYawRateOvershootRadPerSec": 0.0,
  "unsettledPlanarTransitionCount": 0,
  "unsettledYawRateTransitionCount": 0,
  "initialBasePosition": [
    0.0,
    0.0,
    0.44
  ],
  "finalBasePosition": [
    0.36301064039209613,
    -0.01629800414268715,
    0.18006991373417383
  ],
  "netDisplacement": [
    0.36301064039209613,
    -0.01629800414268715,
    -0.25993008626582614
  ],
  "targetPlanarDisplacement": [
    1.25,
    0.0
  ],
  "forwardDisplacement": 0.36301064039209613,
  "targetDistance": 1.25,
  "forwardProgress": 0.2904085123136769,
  "signedForwardProgress": 0.2904085123136769,
  "backwardDisplacement": 0.0,
  "meanForwardVelocity": 0.19105823178531361,
  "lateralDrift": 0.01629800414268715,
  "distanceTraveled": 0.4227707034866788
}
