{
  "verdict": "REVERT",
  "decision": {
    "verdict": "REVERT",
    "gateReasons": [
      "delayed-forward: planar-velocity-tracking regressed from passing to failing",
      "upright-locomotion: delayed-forward: yaw-rate-tracking regressed from passing to failing",
      "command-transitions: forward-reverse-stop: unsettled-planar regressed from passing to failing",
      "command-transitions: delayed-braking: planar-overshoot regressed from passing to failing"
    ],
    "previousViolationCount": 10,
    "candidateViolationCount": 10,
    "previousViolationSeverity": 7.718768986744092,
    "candidateViolationSeverity": 10.520465341025552,
    "feasibilityImproved": false,
    "severityImproved": false,
    "scoreImproved": false,
    "selectionReason": "gate-regression"
  },
  "revisionId": null
}
